LICENSE
README.md
pyproject.toml
src/mcp/__init__.py
src/mcp/py.typed
src/mcp/cli/__init__.py
src/mcp/cli/claude.py
src/mcp/cli/cli.py
src/mcp/client/__init__.py
src/mcp/client/__main__.py
src/mcp/client/_memory.py
src/mcp/client/client.py
src/mcp/client/session.py
src/mcp/client/session_group.py
src/mcp/client/sse.py
src/mcp/client/stdio.py
src/mcp/client/streamable_http.py
src/mcp/client/websocket.py
src/mcp/client/auth/__init__.py
src/mcp/client/auth/exceptions.py
src/mcp/client/auth/oauth2.py
src/mcp/client/auth/utils.py
src/mcp/client/auth/extensions/__init__.py
src/mcp/client/auth/extensions/client_credentials.py
src/mcp/client/experimental/__init__.py
src/mcp/client/experimental/task_handlers.py
src/mcp/client/experimental/tasks.py
src/mcp/os/__init__.py
src/mcp/os/posix/__init__.py
src/mcp/os/posix/utilities.py
src/mcp/os/win32/__init__.py
src/mcp/os/win32/utilities.py
src/mcp/server/__init__.py
src/mcp/server/__main__.py
src/mcp/server/elicitation.py
src/mcp/server/models.py
src/mcp/server/session.py
src/mcp/server/sse.py
src/mcp/server/stdio.py
src/mcp/server/streamable_http.py
src/mcp/server/streamable_http_manager.py
src/mcp/server/transport_security.py
src/mcp/server/validation.py
src/mcp/server/websocket.py
src/mcp/server/auth/__init__.py
src/mcp/server/auth/errors.py
src/mcp/server/auth/json_response.py
src/mcp/server/auth/provider.py
src/mcp/server/auth/routes.py
src/mcp/server/auth/settings.py
src/mcp/server/auth/handlers/__init__.py
src/mcp/server/auth/handlers/authorize.py
src/mcp/server/auth/handlers/metadata.py
src/mcp/server/auth/handlers/register.py
src/mcp/server/auth/handlers/revoke.py
src/mcp/server/auth/handlers/token.py
src/mcp/server/auth/middleware/__init__.py
src/mcp/server/auth/middleware/auth_context.py
src/mcp/server/auth/middleware/bearer_auth.py
src/mcp/server/auth/middleware/client_auth.py
src/mcp/server/experimental/__init__.py
src/mcp/server/experimental/request_context.py
src/mcp/server/experimental/session_features.py
src/test_package_demo_20260130.egg-info/PKG-INFO
src/test_package_demo_20260130.egg-info/SOURCES.txt
src/test_package_demo_20260130.egg-info/dependency_links.txt
src/test_package_demo_20260130.egg-info/top_level.txt
